selepy/__init__.py
selepy/constants.py
selepy/driver.py
selepy/driver_funcs.py
selepy/driver_handler.py
selepy/selenium_docker_container.py
selepy-0.3.dist-info/DESCRIPTION.rst
selepy-0.3.dist-info/METADATA
selepy-0.3.dist-info/RECORD
selepy-0.3.dist-info/WHEEL
selepy-0.3.dist-info/metadata.json
selepy-0.3.dist-info/top_level.txt
